[{
	"name": "Wesfarmers",
	"location": "Perth, WA",
	"size": "10,001+ employees",
	"industry": "Retail"
},{
	"name": "Aerosonde",
	"location": "Notting Hill, Victoria",
	"size": "11-50 employees",
	"industry": "Aviation & Aerospace"
},{
	"name": "Alinta Energy",
	"location": "Sydney, NSW",
	"size": "501-1,000 employees",
	"industry": "Utilities"
},{
	"name": "Angus & Robertson Bookworld",
	"size": "51-200 employees",
	"industry": "Retail"
},{
	"name": "Ansell",
	"location": "Iselin, New Jersey",
	"size": "10,001+ employees",
	"industry": "Consumer Goods"
},{
	"name": "Appliances Online",
	"size": "201-500 employees",
	"industry": "Retail"
},{
	"name": "Aristocrat",
	"location": "North Ryde, NSW",
	"size": "1,001-5,000 employees",
	"industry": "Gambling & Casinos"
},{
	"name": "Aurizon",
	"location": "Fortitude Valley, Queensland",
	"size": "5,001-10,000 employees",
	"industry": "Transportation/Trucking/Railroad"
},{
	"name": "Australia And New Zealand Banking Group Limited (Anz)",
	"location": "Mumbai, Maharashtra",
	"size": "51-200 employees",
	"industry": "Banking"
},{
	"name": "AACo",
	"location": "Newstead, QLD",
	"size": "501-1,000 employees",
	"industry": "Food Production"
},{
	"name": "AUSTRALIAN DEFENCE INDUSTRIES PTY LTD",
	"location": "Garden Island, NSW",
	"size": "11-50 employees",
	"industry": "Information Technology and Services"
},{
	"name": "APS Industrial - Ramelec HiTech",
	"location": "Melbourne, Victoria",
	"size": "51-200 employees",
	"industry": "Industrial Automation"
},{
	"name": "Australian Pharmaceutical Industries (API)",
	"location": "Melbourne, VIC",
	"size": "1,001-5,000 employees",
	"industry": "Retail"
},{
	"name": "AUSTRALIAN SECURITIES EXCHANGE LIMITED",
	"size": "51-200 employees",
	"industry": "Computer Software"
},{
	"name": "ASC Pty Ltd",
	"location": "Osborne, South Australia",
	"size": "1,001-5,000 employees",
	"industry": "Defense & Space"
},{
	"name": "Ausway Mapping Group",
	"industry": "Publishing"
},{
	"name": "Ausway Mapping Group",
	"industry": "Publishing"
},{
	"name": "BHP",
	"location": "Melbourne, Victoria",
	"size": "10,001+ employees",
	"industry": "Mining & Metals"
},{
	"name": "Blundstone Australia Pty Ltd",
	"location": "Hobart",
	"size": "51-200 employees",
	"industry": "Apparel & Fashion"
},{
	"name": "Boost Juice Bars UK",
	"size": "201-500 employees",
	"industry": "Retail"
},{
	"name": "Boral",
	"size": "10,001+ employees",
	"industry": "Building Materials"
},{
	"name": "Brambles",
	"location": "Sydney, NSW",
	"size": "10,001+ employees",
	"industry": "Logistics and Supply Chain"
},{
	"name": "Bulla Dairy Foods",
	"location": "Derrimut, Victoria",
	"size": "501-1,000 employees",
	"industry": "Dairy"
},{
	"name": "Bunnings",
	"location": "Hawthorn East, Victoria",
	"size": "10,001+ employees",
	"industry": "Retail"
},{
	"name": "CBH Group",
	"location": "West Perth, WA",
	"size": "1,001-5,000 employees",
	"industry": "Logistics and Supply Chain"
},{
	"name": "Cbus Super Fund",
	"location": "Melbourne, VIC",
	"size": "201-500 employees",
	"industry": "Financial Services"
},{
	"name": "Chemeq Limited",
	"location": "Rockingham, WAS",
	"size": "51-200 employees",
	"industry": "Research"
},{
	"name": "CityRail",
	"location": "Fortitude Valley, QLD",
	"size": "51-200 employees",
	"industry": "Transportation/Trucking/Railroad"
},{
	"name": "Commonwealth Bank",
	"location": "Sydney, NSW",
	"size": "10,001+ employees",
	"industry": "Financial Services"
},{
	"name": "Comparethemarket.com.au",
	"location": "Toowong, Queensland",
	"size": "51-200 employees",
	"industry": "Financial Services"
},{
	"name": "Compass Resources",
	"size": "2-10 employees",
	"industry": "Mental Health Care"
},{
	"name": "Cotton On Group",
	"location": "North Geelong, VIC",
	"size": "10,001+ employees",
	"industry": "Apparel & Fashion"
},{
	"name": "Crossecom",
	"industry": "Information Technology and Services"
},{
	"name": "Crumpler Australia",
	"location": "Melbourne, Victoria",
	"size": "51-200 employees",
	"industry": "Consumer Goods"
},{
	"name": "CSL",
	"location": "Melbourne, VIC",
	"size": "10,001+ employees",
	"industry": "Biotechnology"
},{
	"name": "Dick Smith Electronics",
	"size": "1,001-5,000 employees",
	"industry": "Consumer Electronics"
},{
	"name": "Dick Smith Foods Pty Ltd",
	"location": "Belrose, NSW",
	"size": "11-50 employees",
	"industry": "Food & Beverages"
},{
	"name": "Downer",
	"location": "North Ryde, NSW",
	"size": "10,001+ employees",
	"industry": "Civil Engineering"
},{
	"name": "Elders",
	"location": "Adelaide, South Australia",
	"size": "1,001-5,000 employees",
	"industry": "Farming"
},{
	"name": "EnergyAustralia",
	"size": "1,001-5,000 employees",
	"industry": "Utilities"
},{
	"name": "Ergon Energy",
	"location": "Townsville, Qld",
	"size": "1,001-5,000 employees",
	"industry": "Utilities"
},{
	"name": "Fairfax Media",
	"location": "Sydney, New South Wales",
	"size": "5,001-10,000 employees",
	"industry": "Online Media"
},{
	"name": "Fortescue Metals Group",
	"location": "East Perth, Western Australia",
	"size": "1,001-5,000 employees",
	"industry": "Mining & Metals"
},{
	"name": "Foster Group",
	"location": "West Des Moines, IA",
	"size": "51-200 employees",
	"industry": "Financial Services"
},{
	"name": "Foxtel",
	"location": "North Ryde, SYDNEY",
	"size": "1,001-5,000 employees",
	"industry": "Broadcast Media"
},{
	"name": "Franklin Templeton Investments",
	"location": "San Mateo, California",
	"size": "5,001-10,000 employees",
	"industry": "Financial Services"
},{
	"name": "Funnelback",
	"location": "Canberra, ACT",
	"size": "51-200 employees",
	"industry": "Information Technology and Services"
},{
	"name": "GOLDEN NORTH VAN LINES, INC.",
	"location": "Anchorage, Alaska",
	"size": "51-200 employees",
	"industry": "Transportation/Trucking/Railroad"
},{
	"name": "Harvey Norman",
	"location": "Homebush West, NSW",
	"size": "10,001+ employees",
	"industry": "Retail"
},{
	"name": "HSV - Holden Special Vehicles",
	"location": "Melbourne, Vic",
	"size": "51-200 employees",
	"industry": "Automotive"
},{
	"name": "IAG",
	"location": "Sydney, NSW",
	"size": "10,001+ employees",
	"industry": "Insurance"
},{
	"name": "The iQ Group Global",
	"location": "Sydney, NSW",
	"size": "51-200 employees",
	"industry": "Biotechnology"
},{
	"name": "JB Hi-Fi",
	"size": "5,001-10,000 employees",
	"industry": "Consumer Electronics"
},{
	"name": "King Living",
	"size": "201-500 employees",
	"industry": "Furniture"
},{
	"name": "Kleenmaid",
	"size": "1,001-5,000 employees",
	"industry": "Retail"
},{
	"name": "Kogan.com",
	"location": "South Melbourne, VIC",
	"size": "51-200 employees",
	"industry": "Retail"
},{
	"name": "LJ Hooker",
	"location": "Alexandria, NSW",
	"size": "5,001-10,000 employees",
	"industry": "Real Estate"
},{
	"name": "Bogala Graphite Lanka PLC"
},{
	"name": "Leading Edge Group",
	"location": "Cobh, Cork",
	"size": "11-50 employees",
	"industry": "Management Consulting"
},{
	"name": "Lendlease",
	"location": "Barangaroo, NSW",
	"size": "10,001+ employees",
	"industry": "Construction"
},{
	"name": "Lion",
	"location": "Sydney, NSW",
	"size": "5,001-10,000 employees",
	"industry": "Food & Beverages"
},{
	"name": "MAB Corporation",
	"location": "MELBOURNE, VIC",
	"size": "51-200 employees",
	"industry": "Real Estate"
},{
	"name": "Macquarie Group",
	"location": "Sydney, NSW",
	"size": "10,001+ employees",
	"industry": "Financial Services"
},{
	"name": "Maton Guitars",
	"location": "Box Hill, Victoria",
	"size": "51-200 employees",
	"industry": "Music"
},{
	"name": "MediaPoint",
	"size": "11-50 employees",
	"industry": "Online Media"
},{
	"name": "Melbourne IT Group",
	"location": "Melbourne, VIC",
	"size": "501-1,000 employees",
	"industry": "Information Technology and Services"
},{
	"name": "Meriton Group",
	"location": "Sydney, NSW",
	"size": "501-1,000 employees",
	"industry": "Real Estate"
},{
	"name": "Metalstorm Inc",
	"location": "Green Bay, WI",
	"size": "2-10 employees",
	"industry": "Mining & Metals"
},{
	"name": "Mirvac",
	"size": "1,001-5,000 employees",
	"industry": "Real Estate"
},{
	"name": "Multiplex",
	"location": "Sydney, NSW",
	"size": "1,001-5,000 employees",
	"industry": "Construction"
},{
	"name": "Murrays Coaches",
	"location": "Symonston, ACT",
	"size": "201-500 employees",
	"industry": "Transportation/Trucking/Railroad"
},{
	"name": "MYER",
	"location": "Docklands, Victoria",
	"size": "10,001+ employees",
	"industry": "Retail"
},{
	"name": "MYOB",
	"location": "Cremorne, Victoria",
	"size": "1,001-5,000 employees",
	"industry": "Computer Software"
},{
	"name": "National Australia Bank",
	"location": "Melbourne, Victoria",
	"size": "10,001+ employees",
	"industry": "Banking"
},{
	"name": "National Storage",
	"location": "Brisbane, QLD",
	"size": "201-500 employees",
	"industry": "Warehousing"
},{
	"name": "Netbox Blue",
	"location": "Spring Hill, Queensland",
	"size": "11-50 employees",
	"industry": "Information Technology and Services"
},{
	"name": "Network Ten",
	"location": "Pyrmont, NSW",
	"size": "1,001-5,000 employees",
	"industry": "Broadcast Media"
},{
	"name": "Newcrest Mining",
	"location": "Melbourne, Victoria",
	"size": "10,001+ employees",
	"industry": "Mining & Metals"
},{
	"name": "Nine Network of Public Media",
	"location": "Saint Louis, Missouri",
	"size": "11-50 employees",
	"industry": "Media Production"
},{
	"name": "Nufarm",
	"location": "Laverton North, VIC",
	"size": "1,001-5,000 employees",
	"industry": "Chemicals"
},{
	"name": "OCTAVIAR LIMITED",
	"location": "Sydney, New South Wales",
	"size": "11-50 employees",
	"industry": "Information Technology and Services"
},{
	"name": "Office National",
	"location": "Johannesburg, Gauteng",
	"size": "501-1,000 employees",
	"industry": "Business Supplies and Equipment"
},{
	"name": "Officeworks",
	"location": "East Bentleigh, VIC",
	"size": "5,001-10,000 employees",
	"industry": "Retail"
},{
	"name": "Oneflare",
	"location": "Sydney, NSW",
	"size": "51-200 employees",
	"industry": "Consumer Services"
},{
	"name": "Porto Central",
	"location": "Vitoria, Espirito Santo",
	"size": "11-50 employees",
	"industry": "Maritime"
},{
	"name": "Optus",
	"location": "Macquarie Park, NSW",
	"size": "10,001+ employees",
	"industry": "Telecommunications"
},{
	"name": "Orbital UAV",
	"location": "Balcatta, Western Australia",
	"size": "11-50 employees",
	"industry": "Aviation & Aerospace"
},{
	"name": "Orica",
	"location": "East Melbourne, Victoria",
	"size": "10,001+ employees",
	"industry": "Mining & Metals"
},{
	"name": "Origin Energy",
	"location": "Sydney, NSW",
	"size": "5,001-10,000 employees",
	"industry": "Oil & Energy"
},{
	"name": "Orocobre Limited",
	"location": "Brisbane, Queensland",
	"size": "201-500 employees",
	"industry": "Chemicals"
},{
	"name": "1116 SEN",
	"location": "Richmond, VIC",
	"size": "51-200 employees",
	"industry": "Broadcast Media"
},{
	"name": "People Telecom",
	"size": "51-200 employees",
	"industry": "Telecommunications"
},{
	"name": "Peter Lehmann Wines",
	"location": "Tanunda, SA",
	"size": "51-200 employees",
	"industry": "Wine and Spirits"
},{
	"name": "HomePipe Networks Inc.",
	"location": "Seattle, WA",
	"size": "2-10 employees",
	"industry": "Computer Software"
},{
	"name": "Prominate",
	"location": "Luton, Bedfordshire",
	"size": "1,001-5,000 employees",
	"industry": "Marketing and Advertising"
},{
	"name": "Qantas",
	"location": "Mascot, NSW",
	"size": "10,001+ employees",
	"industry": "Airlines/Aviation"
},{
	"name": "Queensland Rail",
	"location": "Brisbane, Queensland",
	"size": "5,001-10,000 employees",
	"industry": "Transportation/Trucking/Railroad"
},{
	"name": "Rail Infrastructure Corporation",
	"size": "2-10 employees",
	"industry": "Internet"
},{
	"name": "Ramsay Health Care",
	"size": "10,001+ employees",
	"industry": "Hospital & Health Care"
},{
	"name": "Red Rooster",
	"location": "CHATSWOOD, NSW",
	"size": "5,001-10,000 employees",
	"industry": "Restaurants"
},{
	"name": "Redbubble",
	"location": "Melbourne, Victoria",
	"size": "51-200 employees",
	"industry": "Internet"
},{
	"name": "NCCER",
	"location": "Alachua, FL",
	"size": "51-200 employees",
	"industry": "Construction"
},{
	"name": "Rio Tinto",
	"location": "London, Greater London",
	"size": "10,001+ employees",
	"industry": "Mining & Metals"
},{
	"name": "Rip Curl",
	"location": "Torquay, Victoria",
	"size": "51-200 employees",
	"industry": "Apparel & Fashion"
},{
	"name": "Roy Morgan",
	"location": "VIC, 3000",
	"size": "201-500 employees",
	"industry": "Market Research"
},{
	"name": "Sanitarium",
	"location": "Berkeley Vale, NSW",
	"size": "1,001-5,000 employees",
	"industry": "Food Production"
},{
	"name": "Santos Ltd",
	"location": "Adelaide, South Australia",
	"size": "1,001-5,000 employees",
	"industry": "Oil & Energy"
},{
	"name": "SAUSAGE SOFTWARE LTD",
	"location": "\u77f3\u5bb6\u5e84, \u6cb3\u5317\u7701",
	"size": "51-200 employees",
	"industry": "Telecommunications"
},{
	"name": "Scentre Group (Owner and Operator of Westfield in Aus and NZ)",
	"location": "Sydney, NSW",
	"size": "1,001-5,000 employees",
	"industry": "Real Estate"
},{
	"name": "Searle x Waldron Architecture",
	"location": "Melbourne, VIC",
	"size": "2-10 employees",
	"industry": "Architecture & Planning"
},{
	"name": "Seven Network",
	"location": "Sydney, New South Wales",
	"size": "1,001-5,000 employees",
	"industry": "Broadcast Media"
},{
	"name": "Sigma Pharmaceuticals, LLC",
	"location": "North Liberty, Iowa",
	"size": "2-10 employees",
	"industry": "Pharmaceuticals"
},{
	"name": "Sino Gold Mining Limited",
	"size": "1,001-5,000 employees",
	"industry": "Mining & Metals"
},{
	"name": "Slater and Gordon Lawyers",
	"location": "Melbourne, Victoria",
	"size": "501-1,000 employees",
	"industry": "Law Practice"
},{
	"name": "Smorgon Steel",
	"size": "1,001-5,000 employees",
	"industry": "Mining & Metals"
},{
	"name": "Snowy Hydro Limited",
	"location": "Cooma, NSW",
	"size": "501-1,000 employees",
	"industry": "Utilities"
},{
	"name": "Durango & Silverton Narrow Gauge Railroad",
	"size": "51-200 employees",
	"industry": "Transportation/Trucking/Railroad"
},{
	"name": "SPC Ardmona",
	"location": "Melbourne, Victoria",
	"size": "501-1,000 employees",
	"industry": "Food & Beverages"
},{
	"name": "Special Broadcasting Service (SBS) Australia",
	"location": "Sydney, NSW",
	"size": "1,001-5,000 employees",
	"industry": "Broadcast Media"
},{
	"name": "St.George Bank",
	"location": "Sydney, NSW",
	"size": "5,001-10,000 employees",
	"industry": "Banking"
},{
	"name": "Stanwell Corporation Limited",
	"location": "Queensland",
	"size": "501-1,000 employees",
	"industry": "Utilities"
},{
	"name": "The Star Entertainment Group",
	"location": "Pyrmont, NSW",
	"size": "5,001-10,000 employees",
	"industry": "Gambling & Casinos"
},{
	"name": "STING SPORTS",
	"location": "Melbourne, Victoria",
	"size": "11-50 employees",
	"industry": "Sporting Goods"
},{
	"name": "Strategic Marine",
	"location": "Singapore, Singapore",
	"size": "501-1,000 employees",
	"industry": "Shipbuilding"
},{
	"name": "Suncorp Group",
	"location": "Auckland",
	"size": "10,001+ employees",
	"industry": "Financial Services"
},{
	"name": "Sunland Group",
	"location": "Benowa, Queensland",
	"size": "51-200 employees",
	"industry": "Real Estate"
},{
	"name": "Sydney Ferries",
	"size": "501-1,000 employees",
	"industry": "Transportation/Trucking/Railroad"
},{
	"name": "Sydney Water",
	"location": "Parramatta, New South Wales",
	"size": "1,001-5,000 employees",
	"industry": "Utilities"
},{
	"name": "Tabcorp",
	"location": "Melbourne, Victoria",
	"size": "1,001-5,000 employees",
	"industry": "Entertainment"
},{
	"name": "Target Australia",
	"location": "North Geelong, VIC",
	"size": "10,001+ employees",
	"industry": "Retail"
},{
	"name": "TAROCASH",
	"size": "1,001-5,000 employees",
	"industry": "Retail"
},{
	"name": "Tatts Group",
	"location": "Brisbane, QLD",
	"size": "1,001-5,000 employees",
	"industry": "Gambling & Casinos"
},{
	"name": "TechnologyOne",
	"location": "Fortitude Valley, QLD",
	"size": "1,001-5,000 employees",
	"industry": "Computer Software"
},{
	"name": "Telstra",
	"location": "Sydney, NSW",
	"size": "10,001+ employees",
	"industry": "Telecommunications"
},{
	"name": "Tenix LADS Corporation Pty. Ltd.",
	"location": "Mawson Lakes, South Australia",
	"size": "2-10 employees",
	"industry": "Environmental Services"
},{
	"name": "Tip Top Bakeries",
	"location": "Eaglehawk, VIC",
	"size": "201-500 employees"
},{
	"name": "Toll Group",
	"location": "Melbourne, VIC",
	"size": "10,001+ employees",
	"industry": "Logistics and Supply Chain"
},{
	"name": "Torus Games",
	"location": "Bayswater, Victoria",
	"size": "11-50 employees",
	"industry": "Computer Games"
},{
	"name": "TPG Telecom",
	"location": "Sydney, New South Wales",
	"size": "1,001-5,000 employees",
	"industry": "Telecommunications"
},{
	"name": "Transperth Ferry",
	"location": "Perth, Western Australia",
	"industry": "Oil & Energy"
},{
	"name": "Transurban",
	"location": "Melbourne, Victoria",
	"size": "1,001-5,000 employees",
	"industry": "Transportation/Trucking/Railroad"
},{
	"name": "United Global Logistics (UGL) Ltd.",
	"size": "2-10 employees",
	"industry": "Transportation/Trucking/Railroad"
},{
	"name": "Vero",
	"size": "1,001-5,000 employees",
	"industry": "Insurance"
},{
	"name": "Vicinity Centres",
	"location": "Chadstone, Victoria",
	"size": "1,001-5,000 employees",
	"industry": "Commercial Real Estate"
},{
	"name": "Village Cinemas Australia",
	"size": "501-1,000 employees",
	"industry": "Entertainment"
},{
	"name": "Village Roadshow",
	"location": "South Yarra, Victoria",
	"size": "1,001-5,000 employees",
	"industry": "Entertainment"
},{
	"name": "Virgin Australia",
	"location": "Brisbane, Queensland",
	"size": "5,001-10,000 employees",
	"industry": "Airlines/Aviation"
},{
	"name": "Visual Obsession Pty Ltd",
	"location": "Cairns, QLD",
	"size": "11-50 employees",
	"industry": "Media Production"
},{
	"name": "Valspar Paint Services Pty Ltd",
	"size": "1,001-5,000 employees",
	"industry": "Chemicals"
},{
	"name": "Webjet.com.au",
	"location": "Melbourne, VIC",
	"size": "51-200 employees",
	"industry": "Leisure, Travel & Tourism"
},{
	"name": "Wesfarmers",
	"location": "Perth, WA",
	"size": "10,001+ employees",
	"industry": "Retail"
},{
	"name": "Westnet",
	"size": "201-500 employees",
	"industry": "Telecommunications"
},{
	"name": "Westpac",
	"location": "Sydney, NSW",
	"size": "10,001+ employees",
	"industry": "Banking"
},{
	"name": "Wine Selectors",
	"location": "Newcastle, NSW",
	"size": "201-500 employees",
	"industry": "Food & Beverages"
},{
	"name": "Winning Appliances",
	"location": "Redfern, NSW",
	"size": "51-200 employees",
	"industry": "Retail"
},{
	"name": "Woods Bagot",
	"location": "Global Studio",
	"size": "501-1,000 employees",
	"industry": "Architecture & Planning"
},{
	"name": "Woodside Energy",
	"location": "Perth, Western Australia",
	"size": "1,001-5,000 employees",
	"industry": "Oil & Energy"
},{
	"name": "Woolworths Group",
	"location": "Bella Vista, NSW",
	"size": "10,001+ employees",
	"industry": "Retail"
},{
	"name": "WorleyParsons",
	"location": "North Sydney, NSW",
	"size": "10,001+ employees",
	"industry": "Oil & Energy"
},{
	"name": "Ace Radio",
	"size": "11-50 employees",
	"industry": "Broadcast Media"
},{
	"name": "Altium\u00ae",
	"location": "La Jolla, California",
	"size": "501-1,000 employees",
	"industry": "Computer Software"
},{
	"name": "Alumina Limited",
	"industry": "Mining & Metals"
},{
	"name": "Ansarada",
	"location": "The Rocks, Sydney, NSW",
	"size": "51-200 employees",
	"industry": "Information Technology and Services"
},{
	"name": "Arnotts",
	"location": "Dublin 1",
	"size": "501-1,000 employees",
	"industry": "Retail"
},{
	"name": "Arrium",
	"location": "St Leonards, NSW",
	"size": "10,001+ employees",
	"industry": "Mining & Metals"
},{
	"name": "Atlassian",
	"location": "Sydney, NSW",
	"size": "1,001-5,000 employees",
	"industry": "Computer Software"
},{
	"name": "Austal",
	"location": "Henderson, Western Australia",
	"size": "5,001-10,000 employees",
	"industry": "Shipbuilding"
},{
	"name": "Austrian Airlines",
	"location": "Vienna",
	"size": "5,001-10,000 employees",
	"industry": "Airlines/Aviation"
},{
	"name": "Australian Broadcasting Corporation (ABC)",
	"location": "Ultimo, NSW",
	"size": "1,001-5,000 employees",
	"industry": "Broadcast Media"
},{
	"name": "AWB",
	"size": "1,001-5,000 employees",
	"industry": "Consumer Goods"
},{
	"name": "Bank of Queensland",
	"location": "Newstead, QLD",
	"size": "1,001-5,000 employees",
	"industry": "Financial Services"
},{
	"name": "Billabong",
	"location": "Irvine, CA",
	"size": "5,001-10,000 employees",
	"industry": "Apparel & Fashion"
},{
	"name": "CIMIC Group Limited",
	"location": "North Sydney, NSW",
	"size": "10,001+ employees",
	"industry": "Civil Engineering"
},{
	"name": "Crazy John's",
	"location": "Port Melbourne, Victoria",
	"size": "501-1,000 employees",
	"industry": "Telecommunications"
},{
	"name": "Crown Resorts",
	"location": "Melbourne, Victoria",
	"size": "10,001+ employees",
	"industry": "Gambling & Casinos"
},{
	"name": "David Jones",
	"location": "Burnley, Victoria",
	"size": "5,001-10,000 employees",
	"industry": "Retail"
},{
	"name": "Eagle Boys",
	"location": "Brisbane, Queensland",
	"size": "1,001-5,000 employees",
	"industry": "Retail"
},{
	"name": "EFTel",
	"size": "51-200 employees",
	"industry": "Information Technology and Services"
},{
	"name": "Elfin Sports Cars Pty Ltd.",
	"location": "Braeside, Victoria",
	"size": "2-10 employees",
	"industry": "Automotive"
},{
	"name": "EnviroMission Limited",
	"location": "South Melbourne, Victoria",
	"size": "2-10 employees",
	"industry": "Renewables & Environment"
},{
	"name": "Eraring Energy",
	"location": "Eraring, NSW",
	"size": "1,001-5,000 employees",
	"industry": "Oil & Energy"
},{
	"name": "Foodland Supermarkets Australia",
	"size": "5,001-10,000 employees",
	"industry": "Retail"
},{
	"name": "Halfbrick",
	"location": "Brisbane",
	"size": "51-200 employees",
	"industry": "Computer Games"
},{
	"name": "Healthscope",
	"location": "Melbourne, Victoria",
	"size": "10,001+ employees",
	"industry": "Hospital & Health Care"
},{
	"name": "Incat Crowther",
	"location": "Belrose, NSW",
	"size": "11-50 employees",
	"industry": "Shipbuilding"
},{
	"name": "Incitec Pivot Limited",
	"location": "Southbank, Victoria",
	"size": "1,001-5,000 employees",
	"industry": "Chemicals"
},{
	"name": "IOOF Holdings Ltd",
	"location": "Melbourne, Victoria",
	"size": "1,001-5,000 employees",
	"industry": "Financial Services"
},{
	"name": "Jetstar Airways",
	"location": "Collingwood, Victoria",
	"size": "5,001-10,000 employees",
	"industry": "Airlines/Aviation"
},{
	"name": "Woolworths",
	"location": "Cape Town, Western Cape",
	"size": "10,001+ employees",
	"industry": "Retail"
},{
	"name": "Commonwealth Bank",
	"location": "Sydney, NSW",
	"size": "10,001+ employees",
	"industry": "Financial Services"
},{
	"name": "National Australia Bank",
	"location": "Melbourne, Victoria",
	"size": "10,001+ employees",
	"industry": "Banking"
},{
	"name": "ABB Grain Limited - page no longer active",
	"location": "Adelaide",
	"size": "1,001-5,000 employees",
	"industry": "Import and Export"
},{
	"name": "ABC Learning Centres NZ Ltd",
	"size": "1,001-5,000 employees",
	"industry": "Education Management"
},{
	"name": "Adam Datacenter | Housing - IaaS - Communications",
	"location": "Barcelona, Barcelona",
	"size": "51-200 employees",
	"industry": "Information Technology and Services"
},{
	"name": "AGL Energy",
	"location": "Sydney, NSW",
	"size": "1,001-5,000 employees",
	"industry": "Utilities"
},{
	"name": "Allphones",
	"size": "501-1,000 employees",
	"industry": "Telecommunications"
},{
	"name": "Amcor",
	"location": "Melbourne, Victoria",
	"size": "10,001+ employees",
	"industry": "Packaging and Containers"
},{
	"name": "AMP",
	"location": "Sydney, NSW",
	"size": "5,001-10,000 employees",
	"industry": "Financial Services"
},{
	"name": "Austar",
	"location": "Sydney, NSW",
	"size": "501-1,000 employees",
	"industry": "Broadcast Media"
},{
	"name": "Australian Radio Network",
	"location": "North Ryde, New South Wales",
	"size": "201-500 employees",
	"industry": "Entertainment"
},{
	"name": "Australia Post",
	"location": "Melbourne, VICTORIA",
	"size": "10,001+ employees",
	"industry": "Consumer Services"
},{
	"name": "Australian Air Express",
	"location": "Level 7, 440 Elizabeth St, Melbourne, Victoria",
	"size": "1,001-5,000 employees",
	"industry": "Logistics and Supply Chain"
},{
	"name": "Australian Ethical Investment",
	"location": "Sydney, NSW",
	"size": "51-200 employees",
	"industry": "Financial Services"
},{
	"name": "Babcock & Brown",
	"size": "1,001-5,000 employees",
	"industry": "Investment Banking"
},{
	"name": "BAE Systems Australia",
	"location": "Edinburgh, SA",
	"size": "1,001-5,000 employees",
	"industry": "Defense & Space"
},{
	"name": "Beaurepaires Australia",
	"location": "Melbourne, Victoria",
	"size": "201-500 employees",
	"industry": "Automotive"
},{
	"name": "Becker Entertainment",
	"location": "Chicago, IL",
	"size": "2-10 employees",
	"industry": "Entertainment"
},{
	"name": "Bing Lee Electrics",
	"industry": "Consumer Electronics"
},{
	"name": "Biosis Pty Ltd",
	"size": "51-200 employees",
	"industry": "Environmental Services"
},{
	"name": "BlueScope",
	"location": "Melbourne, Victoria",
	"size": "10,001+ employees",
	"industry": "Building Materials"
},{
	"name": "Brown Brothers Milawa Vineyard",
	"location": "Milawa, Victoria",
	"size": "201-500 employees",
	"industry": "Wine and Spirits"
},{
	"name": "Burns Philp Food Inc",
	"location": "Fenton, Missouri",
	"size": "11-50 employees",
	"industry": "Information Technology and Services"
},{
	"name": "Canva",
	"location": "Surry Hills, NSW",
	"size": "201-500 employees",
	"industry": "Computer Software"
},{
	"name": "CHEP Australia",
	"location": "Sydney, NSW",
	"size": "5,001-10,000 employees",
	"industry": "Logistics and Supply Chain"
},{
	"name": "Coca-Cola Amatil",
	"location": "North Sydney, NSW",
	"size": "10,001+ employees",
	"industry": "Food & Beverages"
},{
	"name": "Cochlear",
	"location": "North Ryde, NSW",
	"size": "1,001-5,000 employees",
	"industry": "Medical Devices"
},{
	"name": "Coles",
	"location": "Melbourne, VIC",
	"size": "10,001+ employees",
	"industry": "Retail"
}]