{"jobTitle": "Staff  and  Community Giving Officer, UNSW Alumni  and  Engagement", "company": "UNSW", "Detail": {"industry": ["Fund-Raising", "NonprofitOrganizationManagement", "Philanthropy"], "jobFunction": ["Sales", "BusinessDevelopment"], "jobType": "Full-time", "level": "Associate"}, "jobId": "864807604", "location": "Melbourne,AU", "view": "14views"}{"jobTitle": "Store Manager - BWS Bentleigh", "company": "BWS", "Detail": {"industry": ["Food&amp;Beverages", "ConsumerGoods", "Retail"], "jobFunction": ["Sales", "BusinessDevelopment"], "jobType": "Full-time", "level": "Mid-Senior level"}, "jobId": "866983463", "location": "Melbourne,AU", "view": "Posted13hoursago"}{"jobTitle": "Senior Natural Resource Management Officer", "company": "CityofCasey", "Detail": {"industry": ["EnvironmentalServices"], "jobFunction": ["Science"], "jobType": "Full-time", "level": "Mid-Senior level"}, "jobId": "866780136", "location": "NarreWarre", "view": "Posted16hoursago"}{"jobTitle": "Senior SME Sales Consultant", "company": "OriginEnergy", "Detail": {"industry": ["Mining&amp;Metals", "Oil&amp;Energy"], "jobFunction": ["Sales"], "jobType": "Full-time", "level": ""}, "jobId": "865023376", "location": "Melbourne,AU", "view": "18views"}{"jobTitle": "UI Designer", "company": "CreativeRecruiters", "Detail": {"industry": ["OnlineMedia", "Design", "MarketingandAdvertising"], "jobFunction": ["Design", "Advertising"], "jobType": "Temporary", "level": "Mid-Senior level"}, "jobId": "866955206", "location": "Melbourne,Australia", "view": "Posted14hoursago"}{"jobTitle": "Financial Analyst", "company": "RenaultAustralia", "Detail": {"industry": ["Automotive"], "jobFunction": ["BusinessDevelopment", "Sales"], "jobType": "Full-time", "level": "Mid-Senior level"}, "jobId": "865169050", "location": "Melbourne,Australia", "view": "290views"}{"jobTitle": "Director Physician Education", "company": "NorthernHealth", "Detail": {"industry": ["Hospital&amp;HealthCare"], "jobFunction": ["HealthCareProvider"], "jobType": "Full-time", "level": ""}, "jobId": "865030600", "location": "Epping,AU", "view": "26views"}