{"jobTitle": "Mobile Developer/ Support", "company": "EPAMSystems", "Detail": {"industry": ["ComputerSoftware"], "jobFunction": ["InformationTechnology"], "jobType": "Full-time", "level": "Mid-Senior level"}, "jobId": "865035437", "location": "Sydney,Australia", "view": "67views"}{"jobTitle": "Account Manager", "company": "SAIGlobal", "Detail": {"industry": ["Accounting", "ManagementConsulting", "InformationServices"], "jobFunction": ["Sales", "CustomerService"], "jobType": "Full-time", "level": "Associate"}, "jobId": "864714544", "location": "Sydney,NewSouthWales,Australia", "view": "52views"}{"jobTitle": "Full Stack PHP Developer", "company": "HydrogenGroup", "Detail": {"industry": ["InformationTechnologyandServices"], "jobFunction": ["Engineering", "InformationTechnology"], "jobType": "Full-time", "level": "Mid-Senior level"}, "jobId": "867038761", "location": "Sydney,AU", "view": "Posted10hoursago"}{"jobTitle": "Contract Drupal Developer", "company": "PreactaRecruitment", "Detail": {"industry": ["ComputerSoftware"], "jobFunction": ["InformationTechnology"], "jobType": "Full-time", "level": "Mid-Senior level"}, "jobId": "866728960", "location": "Sydney,Australia", "view": "Posted18hoursago"}{"jobTitle": "Consultant - Product Development (3 month contract)", "company": "4mationTechnologies", "Detail": {"industry": ["Internet", "InformationTechnologyandServices", "ComputerSoftware"], "jobFunction": ["InformationTechnology", "Consulting", "ProductManagement"], "jobType": "Contract", "level": "Mid-Senior level"}, "jobId": "864706239", "location": "Level328FoveauxStreet,SurryHills,NSW2010,AU", "view": "80views"}{"jobTitle": "Customer Solution Architect - PreSales", "company": "FujitsuAustraliaLimited", "Detail": {"industry": ["InformationTechnologyandServices"], "jobFunction": ["InformationTechnology"], "jobType": "Full-time", "level": "Mid-Senior level"}, "jobId": "864709737", "location": "Canberra,AustralianCapitalTerritory,Australia", "view": "67views"}{"jobTitle": "Graduate Customer Success Executive", "company": "BottomlineTechnologies", "Detail": {"industry": ["ComputerSoftware", "InformationTechnologyandServices"], "jobFunction": ["CustomerService", "Marketing", "Sales"], "jobType": "Part-time", "level": "Entry level"}, "jobId": "866862047", "location": "Sydney,Australia", "view": "Posted14hoursago"}