{"business":[{"jobTitle": "Junior Backend Developer", "company": "IgniteOnline", "Detail": {"industry": ["Internet", "MarketingandAdvertising"], "jobFunction": ["Production", "InformationTechnology", "Analyst"], "jobType": "Full-time", "level": "Mid-Senior level"}, "jobId": "855148365", "location": "Melbourne,Australia", "view": "253views"},{"jobTitle": "Assistant Store Manager, South Wharf Factory Outlet Store", "company": "adidas", "Detail": {"industry": ["ConsumerGoods", "Retail", "SportingGoods"], "jobFunction": ["Sales", "CustomerService"], "jobType": "Full-time", "level": ""}, "jobId": "848855234", "location": "Melbourne,AU", "view": "76views"},{"jobTitle": "Business Development Associate", "company": "Walsh and Company", "Detail": {"industry": ["FinancialServices", "InvestmentManagement"], "jobFunction": ["BusinessDevelopment"], "jobType": "Full-time", "level": "Entry level"}, "jobId": "851304478", "location": "Melbourne,Victoria,Australia", "view": "383views"},{"jobTitle": "Electrical Engineer | Project Leader | Building Services", "company": "AmidaRecruitment", "Detail": {"industry": ["Construction", "MechanicalorIndustrialEngineering", "Electrical/ElectronicManufacturing"], "jobFunction": ["Consulting", "Engineering", "ProjectManagement"], "jobType": "Full-time", "level": "Mid-Senior level"}, "jobId": "856120060", "location": "Melbourne,Australia", "view": "111views"},{"jobTitle": "iOS Developer", "company": "Sportsbet", "Detail": {"industry": ["Entertainment", "Gambling&amp;Casinos", "Internet"], "jobFunction": ["Engineering", "InformationTechnology"], "jobType": "Full-time", "level": ""}, "jobId": "856344020", "location": "Melbourne,AU", "view": "70views"},{"jobTitle": "Recruitment Resourcer", "company": "TandemCorp-formerlyISGManagement", "Detail": {"industry": ["HumanResources"], "jobFunction": ["CustomerService", "HumanResources"], "jobType": "Full-time", "level": "Entry level"}, "jobId": "855042793", "location": "Level1,417StKildaRoad.,Melbourne,VIC3004,AU", "view": "98views"},{"jobTitle": "Audit Senior / Assistant Manager ", "company": "RSMAustralia", "Detail": {"industry": ["Accounting"], "jobFunction": ["Accounting", "Finance"], "jobType": "Full-time", "level": ""}, "jobId": "856343406", "location": "Melbourne,AU", "view": "150views"},{"jobTitle": "Capital Projects  and  Construction Director / Senior Manager\\\\u2013 Dubai. To US $200,000 Base + Bonus  + benefits. Tax Free", "company": "ConsultingPoint", "Detail": {"industry": ["ManagementConsulting", "Telecommunications", "Construction"], "jobFunction": ["Consulting", "Strategy", "Management"], "jobType": "Full-time", "level": "Director"}, "jobId": "855036425", "location": "Melbourne,Victoria,Australia", "view": "694views"},{"jobTitle": "Automation Test Analyst", "company": "Talent", "Detail": {"industry": ["InformationTechnologyandServices"], "jobFunction": ["InformationTechnology"], "jobType": "Contract", "level": ""}, "jobId": "854896519", "location": "Victoria", "view": "183views"},{"jobTitle": "PHP Developer", "company": "Peoplebank", "Detail": {"industry": ["InformationTechnologyandServices", "ComputerSoftware", "ManagementConsulting"], "jobFunction": ["Engineering", "InformationTechnology"], "jobType": "Temporary", "level": "Entry level"}, "jobId": "850664201", "location": "Melbourne,AU", "view": "102views"},{"jobTitle": "`Head of `Billing and Collections/ Senior Credit Controller", "company": "MarlowRecruitment/MarlowH.R.Solutions", "Detail": {"industry": ["Primary/SecondaryEducation", "FinancialServices", "NonprofitOrganizationManagement"], "jobFunction": ["Education", "Administrative", "GeneralBusiness"], "jobType": "Full-time", "level": "Mid-Senior level"}, "jobId": "855817520", "location": "Balaclava,Victoria,Australia", "view": "151views"},{"jobTitle": "Progress Developer", "company": "ProgressivePeople(Australia)PtyLtd", "Detail": {"industry": ["InformationTechnologyandServices"], "jobFunction": ["InformationTechnology"], "jobType": "Full-time", "level": "Mid-Senior level"}, "jobId": "863588352", "location": "Melbourne,Victoria,Australia", "view": "72views"},{"jobTitle": "ServiceNow Consultant", "company": "GreenLightWorldwide", "Detail": {"industry": ["InformationTechnologyandServices"], "jobFunction": ["InformationTechnology"], "jobType": "Contract", "level": "Mid-Senior level"}, "jobId": "856196442", "location": "Melbourne,Victoria,Australia", "view": "136views"},{"jobTitle": "Physiotherapist", "company": "CENTRALGIPPSLANDHEALTHSERVICE", "Detail": {"industry": ["MedicalPractice", "Hospital&amp;HealthCare"], "jobFunction": ["HealthCareProvider"], "jobType": "Full-time", "level": "Associate"}, "jobId": "853538542", "location": "Melbourne,Australia", "view": "51views"},{"jobTitle": "Systems Engineer", "company": "StateTrustees", "Detail": {"industry": ["FinancialServices"], "jobFunction": ["InformationTechnology"], "jobType": "Full-time", "level": "Mid-Senior level"}, "jobId": "853794973", "location": "1McNabAvenue,Footscray,VIC3011,AU", "view": "152views"},{"jobTitle": "HR Officer", "company": "AspectPersonnel", "Detail": {"industry": ["Construction"], "jobFunction": ["Administrative", "HumanResources", "Sales"], "jobType": "Full-time", "level": "Entry level"}, "jobId": "856134739", "location": "Melbourne,Australia", "view": "266views"},{"jobTitle": "Talent Acquisition Specialist (6 month contract)", "company": "Nintex", "Detail": {"industry": ["ComputerSoftware"], "jobFunction": ["InformationTechnology", "HumanResources"], "jobType": "Contract", "level": "Mid-Senior level"}, "jobId": "856134664", "location": "Melbourne,Australia", "view": "97views"},{"jobTitle": "Service Desk Engineer, Managed Services", "company": "CallProcessingSystems-CPS", "Detail": {"industry": ["InformationTechnologyandServices", "Computer&amp;NetworkSecurity"], "jobFunction": ["InformationTechnology", "CustomerService"], "jobType": "Contract", "level": "Mid-Senior level"}, "jobId": "851725353", "location": "Melbourne,Australia", "view": "70views"},{"jobTitle": "Office Manager/PA", "company": "Transpire", "Detail": {"industry": ["InformationTechnologyandServices"], "jobFunction": ["Administrative"], "jobType": "Full-time", "level": "Entry level"}, "jobId": "854881290", "location": "Malvern,Victoria,Australia", "view": "220views"},{"jobTitle": "EDI Transaction Analyst - Accounts Payable", "company": "AltablueAustralia", "Detail": {"industry": ["Oil&amp;Energy", "Accounting"], "jobFunction": ["Accounting"], "jobType": "Contract", "level": "Associate"}, "jobId": "854046240", "location": "MelbourneCBD,Victoria,Australia", "view": "63views"},{"jobTitle": "Childcare Centre Director", "company": "GuardianEarlyLearningGroup", "Detail": {"industry": ["EducationManagement"], "jobFunction": ["Education", "Management", "Other"], "jobType": "Full-time", "level": "Director"}, "jobId": "854036165", "location": "SouthMelbourne,Victoria,Australia", "view": "51views"},{"jobTitle": "Xmas Casual \\\\u2502 Retail Consultant \\\\u2502 Highpoint", "company": "Optus", "Detail": {"industry": ["Telecommunications", "Internet", "InformationTechnologyandServices"], "jobFunction": ["Sales", "BusinessDevelopment"], "jobType": "Full-time", "level": "Entry level"}, "jobId": "852422291", "location": "Melbourne,AU", "view": "50views"},{"jobTitle": "Senior Consultant - IT Audit", "company": "PwCAustralia", "Detail": {"industry": ["ManagementConsulting", "Accounting", "FinancialServices"], "jobFunction": ["Accounting"], "jobType": "Full-time", "level": ""}, "jobId": "856353386", "location": "Melbourne,AU", "view": "54views"},{"jobTitle": "Graduate Program", "company": "DXCTechnology", "Detail": {"industry": ["InformationTechnologyandServices", "ComputerSoftware", "FinancialServices"], "jobFunction": ["Education", "Training"], "jobType": "Full-time", "level": "Internship"}, "jobId": "854945395", "location": "ForestHill,AU", "view": "550views"},{"jobTitle": "Social Media Content Manager  and  Copy Writer", "company": "3PhaseMarketing", "Detail": {"industry": ["MarketingandAdvertising"], "jobFunction": ["Advertising", "Marketing"], "jobType": "Full-time", "level": "Entry level"}, "jobId": "856920014", "location": "Melbourne,Australia", "view": "490views"}]}